{
  "GroupName": "Rogue_Main_Boss",
  "LevelGraph": "Config/Level/Maze/MazeRogue/Maze_Rogue_Group_StartRoom.json",
  "AreaAnchorName": "LevelArea_P80001_F80001002_G18",
  "SaveType": "Permanent",
  "LoadSide": "Server",
  "StreamingTemplateType": "Standard",
  "HoyoGroupLowestLoadPlatformQuality": "VeryLow",
  "AnchorList": [
    {
      "Name": "Anchor1",
      "RotY": 315.0,
      "ID": 1,
      "PosX": -57.01,
      "PosY": -1.055329,
      "PosZ": -93.18
    }
  ],
  "MonsterList": [
    {
      "NPCMonsterID": 1002040,
      "AIConfig": {
        "PathwayList": [],
        "SlaveConfigList": []
      },
      "LoadOnInitial": true,
      "CampID": 3,
      "BattleArea": {
        "GroupID": 1,
        "ID": 1
      },
      "BoardShowList": [
        2
      ],
      "DefaultLookAtMode": "LookPlayer",
      "InteractIconType": "ChatIcon",
      "Name": "Monster5",
      "RotY": 90.0,
      "ID": 200005,
      "PosX": -118.87,
      "PosY": -0.1,
      "PosZ": -73.177
    }
  ],
  "PropList": [
    {
      "Scale": {
        "x": 1.0,
        "y": 1.0,
        "z": 1.0,
        "normalized": {
          "x": 0.577350259,
          "y": 0.577350259,
          "z": 0.577350259,
          "normalized": {
            "x": 0.5773503,
            "y": 0.5773503,
            "z": 0.5773503,
            "magnitude": 1.00000012,
            "sqrMagnitude": 1.00000024
          },
          "magnitude": 0.99999994,
          "sqrMagnitude": 0.99999994
        },
        "magnitude": 1.73205078,
        "sqrMagnitude": 3.0
      },
      "PropID": 100,
      "LoadOnInitial": true,
      "IsOverrideInitLevelGraph": true,
      "InitLevelGraph": "Config/Level/Maze/MazeRogue/Maze_Rogue_Prop_TriggerBuffSelect.json",
      "Trigger": {
        "Radius": 2.0,
        "DimX": 1.0,
        "DimY": 1.0,
        "DimZ": 1.0
      },
      "CampID": 4,
      "OverrideHintRange": -1.0,
      "OverrideSoundRange": -1.0,
      "CustomTriggerMap": {},
      "DialogueTriggerAngle": 120,
      "DialogueGroups": [],
      "TalkDialogGroupIDList": [],
      "ServerInteractVerificationIDList": [],
      "OverrideMapIconType": -1,
      "DialogueTriggerSkipFakeAvatar": true,
      "LookAtPlayerTriggerRadius": 2.0,
      "OverrideLockRaycastOffset": 1.5,
      "Name": "Prop1",
      "RotY": 90.0,
      "ID": 300001,
      "PosX": -34.51,
      "PosY": -2.133952,
      "PosZ": -172.21
    },
    {
      "Scale": {
        "x": 1.0,
        "y": 1.0,
        "z": 1.0,
        "normalized": {
          "x": 0.577350259,
          "y": 0.577350259,
          "z": 0.577350259,
          "normalized": {
            "x": 0.5773503,
            "y": 0.5773503,
            "z": 0.5773503,
            "magnitude": 1.00000012,
            "sqrMagnitude": 1.00000024
          },
          "magnitude": 0.99999994,
          "sqrMagnitude": 0.99999994
        },
        "magnitude": 1.73205078,
        "sqrMagnitude": 3.0
      },
      "PropID": 1000,
      "LoadOnInitial": true,
      "IsOverrideInitLevelGraph": true,
      "InitLevelGraph": "Config/Level/Props/Rogue/InitLevelGraph_Prop_RogueLobby_Portal_01.json",
      "Trigger": {
        "Radius": 2.0,
        "DimX": 1.0,
        "DimY": 1.0,
        "DimZ": 1.0
      },
      "CampID": 4,
      "OverrideHintRange": -1.0,
      "OverrideSoundRange": -1.0,
      "CustomTriggerMap": {},
      "DialogueTriggerAngle": 120,
      "DialogueGroups": [],
      "TalkDialogGroupIDList": [],
      "ServerInteractVerificationIDList": [],
      "OverrideMapIconType": -1,
      "DialogueTriggerSkipFakeAvatar": true,
      "LookAtPlayerTriggerRadius": 2.0,
      "OverrideLockRaycastOffset": 1.5,
      "Name": "Teleport1",
      "RotY": 90.0,
      "ID": 300002,
      "PosX": -124.25,
      "PosY": -0.101088,
      "PosZ": -73.177
    },
    {
      "Scale": {
        "x": 1.0,
        "y": 1.0,
        "z": 1.0,
        "normalized": {
          "x": 0.577350259,
          "y": 0.577350259,
          "z": 0.577350259,
          "normalized": {
            "x": 0.5773503,
            "y": 0.5773503,
            "z": 0.5773503,
            "magnitude": 1.00000012,
            "sqrMagnitude": 1.00000024
          },
          "magnitude": 0.99999994,
          "sqrMagnitude": 0.99999994
        },
        "magnitude": 1.73205078,
        "sqrMagnitude": 3.0
      },
      "PropID": 100025,
      "IsOverrideInitLevelGraph": true,
      "InitLevelGraph": "Config/Level/Props/Chap00/InitLevelGraph_Prop_Chap00_Des_MPRevoverBox_01.json",
      "CampID": 4,
      "EventID": 10001,
      "OverrideHintRange": -1.0,
      "OverrideSoundRange": -1.0,
      "CustomTriggerMap": {},
      "DialogueTriggerAngle": 120,
      "DialogueGroups": [],
      "TalkDialogGroupIDList": [],
      "ServerInteractVerificationIDList": [],
      "OverrideMapIconType": -1,
      "DialogueTriggerSkipFakeAvatar": true,
      "LookAtPlayerTriggerRadius": 2.0,
      "OverrideLockRaycastOffset": 1.5,
      "Name": "Prop7",
      "RotY": 90.0,
      "ID": 300007,
      "PosX": -106.99,
      "PosY": -1.54,
      "PosZ": -92.24
    },
    {
      "Scale": {
        "x": 1.0,
        "y": 1.0,
        "z": 1.0,
        "normalized": {
          "x": 0.577350259,
          "y": 0.577350259,
          "z": 0.577350259,
          "normalized": {
            "x": 0.5773503,
            "y": 0.5773503,
            "z": 0.5773503,
            "magnitude": 1.00000012,
            "sqrMagnitude": 1.00000024
          },
          "magnitude": 0.99999994,
          "sqrMagnitude": 0.99999994
        },
        "magnitude": 1.73205078,
        "sqrMagnitude": 3.0
      },
      "PropID": 100006,
      "LoadOnInitial": true,
      "IsOverrideInitLevelGraph": true,
      "CampID": 4,
      "OverrideHintRange": -1.0,
      "OverrideSoundRange": -1.0,
      "CustomTriggerMap": {},
      "DialogueTriggerAngle": 120,
      "DialogueGroups": [],
      "TalkDialogGroupIDList": [],
      "ServerInteractVerificationIDList": [],
      "OverrideMapIconType": -1,
      "DialogueTriggerSkipFakeAvatar": true,
      "LookAtPlayerTriggerRadius": 2.0,
      "OverrideLockRaycastOffset": 1.5,
      "Name": "Prop3",
      "RotY": 44.99997,
      "ID": 300003,
      "PosX": -62.78,
      "PosY": -1.458,
      "PosZ": -59.19
    },
    {
      "Scale": {
        "x": 1.0,
        "y": 1.0,
        "z": 1.0,
        "normalized": {
          "x": 0.577350259,
          "y": 0.577350259,
          "z": 0.577350259,
          "normalized": {
            "x": 0.5773503,
            "y": 0.5773503,
            "z": 0.5773503,
            "magnitude": 1.00000012,
            "sqrMagnitude": 1.00000024
          },
          "magnitude": 0.99999994,
          "sqrMagnitude": 0.99999994
        },
        "magnitude": 1.73205078,
        "sqrMagnitude": 3.0
      },
      "PropID": 100006,
      "LoadOnInitial": true,
      "IsOverrideInitLevelGraph": true,
      "CampID": 4,
      "OverrideHintRange": -1.0,
      "OverrideSoundRange": -1.0,
      "CustomTriggerMap": {},
      "DialogueTriggerAngle": 120,
      "DialogueGroups": [],
      "TalkDialogGroupIDList": [],
      "ServerInteractVerificationIDList": [],
      "OverrideMapIconType": -1,
      "DialogueTriggerSkipFakeAvatar": true,
      "LookAtPlayerTriggerRadius": 2.0,
      "OverrideLockRaycastOffset": 1.5,
      "Name": "Prop4",
      "RotY": 315.0,
      "ID": 300004,
      "PosX": -91.08,
      "PosY": -1.422585,
      "PosZ": -59.38
    },
    {
      "Scale": {
        "x": 0.8,
        "y": 1.0,
        "z": 1.0,
        "normalized": {
          "x": 0.492365956,
          "y": 0.6154574,
          "z": 0.6154574,
          "normalized": {
            "x": 0.492366,
            "y": 0.6154575,
            "z": 0.6154575,
            "magnitude": 1.0,
            "sqrMagnitude": 1.00000012
          },
          "magnitude": 0.99999994,
          "sqrMagnitude": 0.9999999
        },
        "magnitude": 1.62480772,
        "sqrMagnitude": 2.64
      },
      "PropID": 100006,
      "LoadOnInitial": true,
      "IsOverrideInitLevelGraph": true,
      "CampID": 4,
      "OverrideHintRange": -1.0,
      "OverrideSoundRange": -1.0,
      "CustomTriggerMap": {},
      "DialogueTriggerAngle": 120,
      "DialogueGroups": [],
      "TalkDialogGroupIDList": [],
      "ServerInteractVerificationIDList": [],
      "OverrideMapIconType": -1,
      "DialogueTriggerSkipFakeAvatar": true,
      "LookAtPlayerTriggerRadius": 2.0,
      "OverrideLockRaycastOffset": 1.5,
      "Name": "Prop5",
      "RotY": 90.0,
      "ID": 300005,
      "PosX": -126.962,
      "PosY": -0.1,
      "PosZ": -73.177
    },
    {
      "Scale": {
        "x": 1.0,
        "y": 1.0,
        "z": 1.0,
        "normalized": {
          "x": 0.577350259,
          "y": 0.577350259,
          "z": 0.577350259,
          "normalized": {
            "x": 0.5773503,
            "y": 0.5773503,
            "z": 0.5773503,
            "magnitude": 1.00000012,
            "sqrMagnitude": 1.00000024
          },
          "magnitude": 0.99999994,
          "sqrMagnitude": 0.99999994
        },
        "magnitude": 1.73205078,
        "sqrMagnitude": 3.0
      },
      "PropID": 100021,
      "LoadOnInitial": true,
      "IsOverrideInitLevelGraph": true,
      "CampID": 4,
      "OverrideHintRange": -1.0,
      "OverrideSoundRange": -1.0,
      "CustomTriggerMap": {},
      "DialogueTriggerAngle": 120,
      "DialogueGroups": [],
      "TalkDialogGroupIDList": [],
      "ServerInteractVerificationIDList": [],
      "OverrideMapIconType": -1,
      "DialogueTriggerSkipFakeAvatar": true,
      "LookAtPlayerTriggerRadius": 2.0,
      "OverrideLockRaycastOffset": 1.5,
      "Name": "Prop6",
      "RotY": 17.05255,
      "ID": 300006,
      "PosX": -110.101,
      "PosY": -0.06062,
      "PosZ": -64.49582
    },
    {
      "Scale": {
        "x": 1.0,
        "y": 1.0,
        "z": 1.0,
        "normalized": {
          "x": 0.577350259,
          "y": 0.577350259,
          "z": 0.577350259,
          "normalized": {
            "x": 0.5773503,
            "y": 0.5773503,
            "z": 0.5773503,
            "magnitude": 1.00000012,
            "sqrMagnitude": 1.00000024
          },
          "magnitude": 0.99999994,
          "sqrMagnitude": 0.99999994
        },
        "magnitude": 1.73205078,
        "sqrMagnitude": 3.0
      },
      "PropID": 100006,
      "LoadOnInitial": true,
      "IsOverrideInitLevelGraph": true,
      "InitLevelGraph": "Config/Level/Maze/MazeRogue/Maze_Rogue_Tutorial_BlockLine.json",
      "ValueSource": {
        "Values": [
          {
            "$type": "RPG.GameCore.SharedString",
            "Value": "6,300001",
            "Key": "\u602a\u7269\u6b7b\u4ea1\u6807\u8bb0"
          }
        ],
        "SharedValues": [
          {
            "$type": "RPG.GameCore.SharedString",
            "Value": "6,300001",
            "Key": "\u602a\u7269\u6b7b\u4ea1\u6807\u8bb0"
          }
        ]
      },
      "CampID": 4,
      "OverrideHintRange": -1.0,
      "OverrideSoundRange": -1.0,
      "CustomTriggerMap": {},
      "DialogueTriggerAngle": 120,
      "DialogueGroups": [],
      "TalkDialogGroupIDList": [],
      "ServerInteractVerificationIDList": [],
      "OverrideMapIconType": -1,
      "DialogueTriggerSkipFakeAvatar": true,
      "LookAtPlayerTriggerRadius": 2.0,
      "OverrideLockRaycastOffset": 1.5,
      "Name": "Prop8",
      "RotY": 225.0,
      "ID": 300008,
      "PosX": -88.28999,
      "PosY": -2.962589,
      "PosZ": -84.68
    },
    {
      "Scale": {
        "x": 1.0,
        "y": 1.0,
        "z": 1.0,
        "normalized": {
          "x": 0.577350259,
          "y": 0.577350259,
          "z": 0.577350259,
          "normalized": {
            "x": 0.5773503,
            "y": 0.5773503,
            "z": 0.5773503,
            "magnitude": 1.00000012,
            "sqrMagnitude": 1.00000024
          },
          "magnitude": 0.99999994,
          "sqrMagnitude": 0.99999994
        },
        "magnitude": 1.73205078,
        "sqrMagnitude": 3.0
      },
      "PropID": 100006,
      "LoadOnInitial": true,
      "IsOverrideInitLevelGraph": true,
      "InitLevelGraph": "Config/Level/Maze/MazeRogue/Maze_Rogue_Tutorial_BlockLine.json",
      "ValueSource": {
        "Values": [
          {
            "$type": "RPG.GameCore.SharedString",
            "Value": "7,300001",
            "Key": "\u602a\u7269\u6b7b\u4ea1\u6807\u8bb0"
          }
        ],
        "SharedValues": [
          {
            "$type": "RPG.GameCore.SharedString",
            "Value": "7,300001",
            "Key": "\u602a\u7269\u6b7b\u4ea1\u6807\u8bb0"
          }
        ]
      },
      "CampID": 4,
      "OverrideHintRange": -1.0,
      "OverrideSoundRange": -1.0,
      "CustomTriggerMap": {},
      "DialogueTriggerAngle": 120,
      "DialogueGroups": [],
      "TalkDialogGroupIDList": [],
      "ServerInteractVerificationIDList": [],
      "OverrideMapIconType": -1,
      "DialogueTriggerSkipFakeAvatar": true,
      "LookAtPlayerTriggerRadius": 2.0,
      "OverrideLockRaycastOffset": 1.5,
      "Name": "Prop9",
      "RotY": 97.64559,
      "ID": 300009,
      "PosX": -105.446,
      "PosY": -1.544299,
      "PosZ": -92.597
    },
    {
      "Scale": {
        "x": 1.0,
        "y": 1.0,
        "z": 1.0,
        "normalized": {
          "x": 0.577350259,
          "y": 0.577350259,
          "z": 0.577350259,
          "normalized": {
            "x": 0.5773503,
            "y": 0.5773503,
            "z": 0.5773503,
            "magnitude": 1.00000012,
            "sqrMagnitude": 1.00000024
          },
          "magnitude": 0.99999994,
          "sqrMagnitude": 0.99999994
        },
        "magnitude": 1.73205078,
        "sqrMagnitude": 3.0
      },
      "PropID": 100,
      "IsOverrideInitLevelGraph": true,
      "InitLevelGraph": "Config/Level/Maze/MazeRogueV3/Maze_Rogue_Prop_ElitHint.json",
      "CampID": 4,
      "OverrideHintRange": -1.0,
      "OverrideSoundRange": -1.0,
      "CustomTriggerMap": {},
      "DialogueTriggerAngle": 120,
      "DialogueGroups": [],
      "TalkDialogGroupIDList": [],
      "ServerInteractVerificationIDList": [],
      "OverrideMapIconType": -1,
      "OverrideMapStateIcons": [
        {
          "IconID": 6
        }
      ],
      "DialogueTriggerSkipFakeAvatar": true,
      "LookAtPlayerTriggerRadius": 2.0,
      "OverrideLockRaycastOffset": 1.5,
      "Name": "Prop10",
      "RotY": 90.0,
      "ID": 300010,
      "PosX": -118.87,
      "PosY": -0.1,
      "PosZ": -73.177
    }
  ],
  "DistrictList": [],
  "WaypointList": [],
  "PathwayList": [],
  "BattleAreaList": [],
  "NPCList": [],
  "CrowdList": [],
  "PedestrianList": []
}