{
  "GroupName": "QTEGotchard",
  "LevelGraph": "Config/Level/GroupGraph/F10401001/Group_F10401001_G526.json",
  "AreaAnchorName": "LevelArea_P10401_F10401001_G526",
  "SaveType": "Permanent",
  "SavedValueCondition": {
    "Conditions": [
      {
        "SavedValueName": "FSV_TimeRewind_TutorialFinish",
        "Operation": "Equal",
        "Value": 1
      }
    ],
    "Operation": "And"
  },
  "LoadSide": "Server",
  "LoadOnInitial": true,
  "GroupStateList": [
    {
      "Comment": "\u8d3c\u7075\u62a2\u593a",
      "DstState": 1
    },
    {
      "Comment": "\u6355\u6349\u8d3c\u7075",
      "SrcState": 1,
      "DstState": 2
    },
    {
      "Comment": "\u8d3c\u7075\u5f52\u8fd8",
      "SrcState": 2,
      "DstState": 3
    },
    {
      "Comment": "\u5b9d\u7bb1\u51fa\u73b0",
      "SrcState": 3,
      "DstState": 4
    }
  ],
  "ValueSource": {
    "Values": [
      {
        "$type": "RPG.GameCore.SharedString",
        "Value": "LevelArea_P10401_F10401001_G526,Vcam1",
        "Key": "Vcam1"
      },
      {
        "$type": "RPG.GameCore.SharedString",
        "Value": "LevelArea_P10401_F10401001_G526,Vcam2",
        "Key": "Vcam2"
      },
      {
        "$type": "RPG.GameCore.SharedString",
        "Value": "LevelArea_P10401_F10401001_G526,Vcam3",
        "Key": "Vcam3"
      },
      {
        "$type": "RPG.GameCore.SharedString",
        "Value": "LevelArea_P10401_F10401001_G526,Vcam4",
        "Key": "Vcam4"
      },
      {
        "$type": "RPG.GameCore.SharedString",
        "Value": "FSV_QTEGotchard_RewardGet_02",
        "Key": "FSV_QTEGotchard_RewardGet_ID"
      },
      {
        "$type": "RPG.GameCore.SharedFloat",
        "Value": 2.0,
        "Key": "StruggleDuration"
      },
      {
        "$type": "RPG.GameCore.SharedFloat",
        "Value": -45.0,
        "Key": "Steer2Run"
      },
      {
        "$type": "RPG.GameCore.SharedFloat",
        "Value": 90.0,
        "Key": "Steer2Player"
      },
      {
        "$type": "RPG.GameCore.SharedFloat",
        "Value": -45.0,
        "Key": "Steer2Chest"
      },
      {
        "$type": "RPG.GameCore.SharedFloat",
        "Value": -90.0,
        "Key": "Steer2Leave"
      },
      {
        "$type": "RPG.GameCore.SharedFloat",
        "Value": 45.0,
        "Key": "Steer2PlayerAFReload"
      }
    ],
    "SharedValues": [
      {
        "$type": "RPG.GameCore.SharedString",
        "Value": "LevelArea_P10401_F10401001_G526,Vcam1",
        "Key": "Vcam1"
      },
      {
        "$type": "RPG.GameCore.SharedString",
        "Value": "LevelArea_P10401_F10401001_G526,Vcam2",
        "Key": "Vcam2"
      },
      {
        "$type": "RPG.GameCore.SharedString",
        "Value": "LevelArea_P10401_F10401001_G526,Vcam3",
        "Key": "Vcam3"
      },
      {
        "$type": "RPG.GameCore.SharedString",
        "Value": "LevelArea_P10401_F10401001_G526,Vcam4",
        "Key": "Vcam4"
      },
      {
        "$type": "RPG.GameCore.SharedString",
        "Value": "FSV_QTEGotchard_RewardGet_02",
        "Key": "FSV_QTEGotchard_RewardGet_ID"
      },
      {
        "$type": "RPG.GameCore.SharedFloat",
        "Value": 2.0,
        "Key": "StruggleDuration"
      },
      {
        "$type": "RPG.GameCore.SharedFloat",
        "Value": -45.0,
        "Key": "Steer2Run"
      },
      {
        "$type": "RPG.GameCore.SharedFloat",
        "Value": 90.0,
        "Key": "Steer2Player"
      },
      {
        "$type": "RPG.GameCore.SharedFloat",
        "Value": -45.0,
        "Key": "Steer2Chest"
      },
      {
        "$type": "RPG.GameCore.SharedFloat",
        "Value": -90.0,
        "Key": "Steer2Leave"
      },
      {
        "$type": "RPG.GameCore.SharedFloat",
        "Value": 45.0,
        "Key": "Steer2PlayerAFReload"
      }
    ]
  },
  "ConflictIDList": [],
  "IsHoyoGroup": true,
  "HoyoGroupLowestLoadPlatformQuality": "VeryLow",
  "ConflictWhiteList": [],
  "TagContainer": [
    {
      "Tag": "Group.Level.SpecialGameplay",
      "TagHash": 718389408
    }
  ],
  "AnchorList": [
    {
      "RotX": 9.556735,
      "RotZ": -3.2e-05,
      "Usage": "Camera",
      "LookAtCameraTemplate": "Level/Common_Adventure/Camera_Module/PinballPuzzleCam01.prefab",
      "CustomParameter": {
        "$type": "RPG.GameCore.LevelAnchorCameraParameter",
        "fov": 60.0
      },
      "Name": "Vcam1",
      "RotY": 334.7325,
      "ID": 1,
      "PosX": 138.2399,
      "PosY": 103.6583,
      "PosZ": 338.1097
    },
    {
      "RotX": 9.556735,
      "RotZ": -3.2e-05,
      "Usage": "Camera",
      "LookAtCameraTemplate": "Level/Common_Adventure/Camera_Module/PinballPuzzleCam01.prefab",
      "CustomParameter": {
        "$type": "RPG.GameCore.LevelAnchorCameraParameter",
        "fov": 60.0,
        "AimIsComposer": true,
        "AimHorizontalDamping": 1.0,
        "AimVerticalDamping": 1.0,
        "AimScreenX": 0.5,
        "AimScreenY": 0.5,
        "AimDeadZoneWidth": 0.3,
        "AimDeadZoneHeight": 0.3
      },
      "Name": "Vcam2",
      "RotY": 334.7325,
      "ID": 2,
      "PosX": 138.2399,
      "PosY": 103.6583,
      "PosZ": 338.1097
    },
    {
      "RotX": 9.556735,
      "RotZ": -3.2e-05,
      "Usage": "Camera",
      "LookAtCameraTemplate": "Level/Common_Adventure/Camera_Module/PinballPuzzleCam01.prefab",
      "CustomParameter": {
        "$type": "RPG.GameCore.LevelAnchorCameraParameter",
        "fov": 60.0
      },
      "Name": "Vcam3",
      "RotY": 334.7325,
      "ID": 3,
      "PosX": 138.2399,
      "PosY": 103.6583,
      "PosZ": 338.1097
    },
    {
      "RotX": 9.556735,
      "RotZ": -3.2e-05,
      "Usage": "Camera",
      "LookAtCameraTemplate": "Level/Common_Adventure/Camera_Module/PinballPuzzleCam01.prefab",
      "CustomParameter": {
        "$type": "RPG.GameCore.LevelAnchorCameraParameter",
        "fov": 20.0,
        "AimIsComposer": true,
        "AimHorizontalDamping": 1.0,
        "AimVerticalDamping": 1.0,
        "AimScreenX": 0.5,
        "AimScreenY": 0.5,
        "AimDeadZoneWidth": 0.3,
        "AimDeadZoneHeight": 0.3
      },
      "Name": "Vcam4",
      "RotY": 334.7325,
      "ID": 4,
      "PosX": 138.2399,
      "PosY": 103.6583,
      "PosZ": 338.1097
    }
  ],
  "MonsterList": [],
  "PropList": [
    {
      "Scale": {
        "x": 1.0,
        "y": 1.0,
        "z": 1.0,
        "normalized": {
          "x": 0.577350259,
          "y": 0.577350259,
          "z": 0.577350259,
          "normalized": {
            "x": 0.5773503,
            "y": 0.5773503,
            "z": 0.5773503,
            "magnitude": 1.00000012,
            "sqrMagnitude": 1.00000024
          },
          "magnitude": 0.99999994,
          "sqrMagnitude": 0.99999994
        },
        "magnitude": 1.73205078,
        "sqrMagnitude": 3.0
      },
      "PropID": 60401,
      "LoadOnInitial": true,
      "IsOverrideInitLevelGraph": true,
      "ValueSource": {},
      "CampID": 4,
      "State": "ChestClosed",
      "OverrideHintRange": -1.0,
      "OverrideSoundRange": -1.0,
      "CustomTriggerMap": {},
      "CustomTriggerMapV2": {},
      "StateConfigs": [],
      "DialogueTriggerAngle": 120,
      "DialogueGroups": [],
      "TalkDialogGroupIDList": [],
      "ServerInteractVerificationIDList": [],
      "OverrideMapIconType": -1,
      "DialogueTriggerSkipFakeAvatar": true,
      "DialogueTriggerSkipSpecifiedFakeAvatarList": [],
      "CameraCenterEntityList": [],
      "CameraConfig": {},
      "LookAtPlayerTriggerRadius": 2.0,
      "OverrideLockRaycastOffset": 1.5,
      "SpawnConfig": {
        "EntitySpawnConfig": {
          "NeedBlackIn": true,
          "BlackInDistance": 25.0,
          "NeedFadeIn": true,
          "NeedFadeOut": true
        }
      },
      "Name": "Fake",
      "RotY": 150.7679,
      "ID": 300001,
      "PosX": 137.081,
      "PosY": 102.052,
      "PosZ": 342.911
    },
    {
      "Scale": {
        "x": 0.6,
        "y": 0.6,
        "z": 0.6,
        "normalized": {
          "x": 0.5773503,
          "y": 0.5773503,
          "z": 0.5773503,
          "normalized": {
            "x": 0.577350259,
            "y": 0.577350259,
            "z": 0.577350259,
            "magnitude": 0.99999994,
            "sqrMagnitude": 0.99999994
          },
          "magnitude": 1.00000012,
          "sqrMagnitude": 1.00000024
        },
        "magnitude": 1.03923047,
        "sqrMagnitude": 1.08
      },
      "PropID": 104159,
      "LoadOnInitial": true,
      "ValueSource": {},
      "CampID": 4,
      "OverrideHintRange": -1.0,
      "OverrideSoundRange": -1.0,
      "CustomTriggerMap": {},
      "CustomTriggerMapV2": {},
      "StateConfigs": [],
      "DialogueTriggerAngle": 120,
      "DialogueGroups": [],
      "TalkDialogGroupIDList": [],
      "ServerInteractVerificationIDList": [],
      "OverrideMapIconType": -1,
      "DialogueTriggerSkipFakeAvatar": true,
      "DialogueTriggerSkipSpecifiedFakeAvatarList": [],
      "CameraCenterEntityList": [],
      "CameraConfig": {},
      "LookAtPlayerTriggerRadius": 2.0,
      "OverrideLockRaycastOffset": 1.5,
      "SpawnConfig": {
        "EntitySpawnConfig": {
          "NeedBlackIn": true,
          "BlackInDistance": 25.0,
          "NeedFadeIn": true,
          "NeedFadeOut": true
        }
      },
      "Name": "Coin",
      "RotY": 150.7679,
      "ID": 300002,
      "PosX": 137.081,
      "PosY": 102.152,
      "PosZ": 342.911
    },
    {
      "Scale": {
        "x": 1.0,
        "y": 1.0,
        "z": 1.0,
        "normalized": {
          "x": 0.577350259,
          "y": 0.577350259,
          "z": 0.577350259,
          "normalized": {
            "x": 0.5773503,
            "y": 0.5773503,
            "z": 0.5773503,
            "magnitude": 1.00000012,
            "sqrMagnitude": 1.00000024
          },
          "magnitude": 0.99999994,
          "sqrMagnitude": 0.99999994
        },
        "magnitude": 1.73205078,
        "sqrMagnitude": 3.0
      },
      "PropID": 104102,
      "LoadOnInitial": true,
      "ValueSource": {
        "Values": [
          {
            "$type": "RPG.GameCore.SharedJsonConfig",
            "Value": {
              "$type": "RPG.GameCore.GameLevelObjectRefConfig",
              "GroupID": 526,
              "InstanceID": 1,
              "Type": "Curve"
            },
            "Key": "CurveRef"
          },
          {
            "$type": "RPG.GameCore.SharedInt",
            "Value": 1,
            "Key": "CaughtType"
          }
        ],
        "SharedValues": [
          {
            "$type": "RPG.GameCore.SharedJsonConfig",
            "Value": {
              "$type": "RPG.GameCore.GameLevelObjectRefConfig",
              "GroupID": 526,
              "InstanceID": 1,
              "Type": "Curve"
            },
            "Key": "CurveRef"
          },
          {
            "$type": "RPG.GameCore.SharedInt",
            "Value": 1,
            "Key": "CaughtType"
          }
        ]
      },
      "CampID": 4,
      "OverrideHintRange": -1.0,
      "OverrideSoundRange": -1.0,
      "CustomTriggerMap": {},
      "CustomTriggerMapV2": {},
      "StateConfigs": [],
      "DialogueTriggerAngle": 120,
      "DialogueGroups": [],
      "TalkDialogGroupIDList": [],
      "ServerInteractVerificationIDList": [],
      "OverrideMapIconType": -1,
      "DialogueTriggerSkipFakeAvatar": true,
      "DialogueTriggerSkipSpecifiedFakeAvatarList": [],
      "IsClientOnly": true,
      "CameraCenterEntityList": [],
      "CameraConfig": {},
      "LookAtPlayerTriggerRadius": 2.0,
      "OverrideLockRaycastOffset": 1.5,
      "SpawnConfig": {
        "EntitySpawnConfig": {
          "NeedBlackIn": true,
          "BlackInDistance": 25.0,
          "NeedFadeIn": true,
          "NeedFadeOut": true
        }
      },
      "Name": "MascotSpirits",
      "RotY": 60.7679,
      "ID": 300003,
      "PosX": 135.299,
      "PosY": 102.773,
      "PosZ": 341.915
    },
    {
      "Scale": {
        "x": 1.0,
        "y": 1.0,
        "z": 1.0,
        "normalized": {
          "x": 0.577350259,
          "y": 0.577350259,
          "z": 0.577350259,
          "normalized": {
            "x": 0.5773503,
            "y": 0.5773503,
            "z": 0.5773503,
            "magnitude": 1.00000012,
            "sqrMagnitude": 1.00000024
          },
          "magnitude": 0.99999994,
          "sqrMagnitude": 0.99999994
        },
        "magnitude": 1.73205078,
        "sqrMagnitude": 3.0
      },
      "PropID": 100,
      "LoadOnInitial": true,
      "ValueSource": {},
      "CampID": 4,
      "OverrideHintRange": -1.0,
      "OverrideSoundRange": -1.0,
      "CustomTriggerMap": {},
      "CustomTriggerMapV2": {},
      "StateConfigs": [],
      "DialogueTriggerAngle": 120,
      "DialogueGroups": [],
      "TalkDialogGroupIDList": [],
      "ServerInteractVerificationIDList": [],
      "OverrideMapIconType": -1,
      "DialogueTriggerSkipFakeAvatar": true,
      "DialogueTriggerSkipSpecifiedFakeAvatarList": [],
      "CameraCenterEntityList": [],
      "CameraConfig": {},
      "LookAtPlayerTriggerRadius": 2.0,
      "OverrideLockRaycastOffset": 1.5,
      "SpawnConfig": {
        "EntitySpawnConfig": {
          "NeedBlackIn": true,
          "BlackInDistance": 25.0,
          "NeedFadeIn": true,
          "NeedFadeOut": true
        }
      },
      "Name": "EffectPoint",
      "RotY": 150.7679,
      "ID": 300004,
      "PosX": 137.081,
      "PosY": 102.052,
      "PosZ": 342.911
    }
  ],
  "DistrictList": [
    {
      "Scale": {
        "x": 1.0,
        "y": 1.0,
        "z": 1.0,
        "normalized": {
          "x": 0.577350259,
          "y": 0.577350259,
          "z": 0.577350259,
          "normalized": {
            "x": 0.5773503,
            "y": 0.5773503,
            "z": 0.5773503,
            "magnitude": 1.00000012,
            "sqrMagnitude": 1.00000024
          },
          "magnitude": 0.99999994,
          "sqrMagnitude": 0.99999994
        },
        "magnitude": 1.73205078,
        "sqrMagnitude": 3.0
      },
      "Trigger": {
        "Shape": "GeometrySphere",
        "Radius": 3.0,
        "DimX": 20.0,
        "DimY": 6.0,
        "DimZ": 15.0,
        "PointList": []
      },
      "LoadOnInitial": true,
      "DistrictType": "Level",
      "NPCCrowdRadius": 25.0,
      "ValueSource": {},
      "Name": "District1",
      "RotY": 150.7679,
      "ID": 1,
      "PosX": 137.081,
      "PosY": 102.052,
      "PosZ": 342.911
    }
  ],
  "WaypointList": [],
  "PathwayList": [],
  "BattleAreaList": [],
  "NPCList": [],
  "CrowdList": [],
  "PedestrianList": [],
  "PedestrianV2List": [],
  "AudienceList": [],
  "SmartObjectList": [],
  "CurveList": [
    {
      "PointList": [
        {
          "Position": {
            "x": -17.99557,
            "y": 11.93462,
            "z": 2.758716,
            "normalized": {
              "x": -0.826663136,
              "y": 0.5482411,
              "z": 0.126727238,
              "magnitude": 1.0,
              "sqrMagnitude": 1.0
            },
            "magnitude": 21.7689266,
            "sqrMagnitude": 473.886169
          },
          "ControlType": 1,
          "Control1": {
            "x": -1.714327,
            "z": 0.056863,
            "normalized": {
              "x": -0.9994503,
              "z": 0.0331510529,
              "normalized": {
                "x": -0.9994504,
                "z": 0.0331510566,
                "magnitude": 1.0,
                "sqrMagnitude": 1.00000012
              },
              "magnitude": 0.99999994,
              "sqrMagnitude": 0.99999994
            },
            "magnitude": 1.7152698,
            "sqrMagnitude": 2.94215035
          },
          "Control2": {
            "x": 1.714327,
            "z": -0.056863,
            "normalized": {
              "x": 0.9994503,
              "z": -0.0331510529,
              "normalized": {
                "x": 0.9994504,
                "z": -0.0331510566,
                "magnitude": 1.0,
                "sqrMagnitude": 1.00000012
              },
              "magnitude": 0.99999994,
              "sqrMagnitude": 0.99999994
            },
            "magnitude": 1.7152698,
            "sqrMagnitude": 2.94215035
          },
          "Alias": "Start"
        },
        {
          "Position": {
            "x": -14.11025,
            "y": 11.93815,
            "z": 2.651766,
            "normalized": {
              "x": -0.755682945,
              "y": 0.6393548,
              "z": 0.142016917,
              "magnitude": 1.0,
              "sqrMagnitude": 1.00000012
            },
            "magnitude": 18.672184,
            "sqrMagnitude": 348.650452
          },
          "ControlType": 1,
          "Control1": {
            "x": -1.714327,
            "z": 0.056863,
            "normalized": {
              "x": -0.9994503,
              "z": 0.0331510529,
              "normalized": {
                "x": -0.9994504,
                "z": 0.0331510566,
                "magnitude": 1.0,
                "sqrMagnitude": 1.00000012
              },
              "magnitude": 0.99999994,
              "sqrMagnitude": 0.99999994
            },
            "magnitude": 1.7152698,
            "sqrMagnitude": 2.94215035
          },
          "Control2": {
            "x": 1.714327,
            "z": -0.056863,
            "normalized": {
              "x": 0.9994503,
              "z": -0.0331510529,
              "normalized": {
                "x": 0.9994504,
                "z": -0.0331510566,
                "magnitude": 1.0,
                "sqrMagnitude": 1.00000012
              },
              "magnitude": 0.99999994,
              "sqrMagnitude": 0.99999994
            },
            "magnitude": 1.7152698,
            "sqrMagnitude": 2.94215035
          }
        },
        {
          "Position": {
            "x": -1.418395,
            "y": 3.370918,
            "z": -2.04309,
            "normalized": {
              "x": -0.3385861,
              "y": 0.804674268,
              "z": -0.487707525,
              "normalized": {
                "x": -0.338586122,
                "y": 0.8046743,
                "z": -0.487707555,
                "magnitude": 1.0,
                "sqrMagnitude": 1.0
              },
              "magnitude": 0.99999994,
              "sqrMagnitude": 0.9999999
            },
            "magnitude": 4.189171,
            "sqrMagnitude": 17.54915
          },
          "ControlType": 1,
          "Control1": {
            "x": -1.795081,
            "y": 1.212349,
            "z": 0.428739,
            "normalized": {
              "x": -0.812934637,
              "y": 0.549034059,
              "z": 0.19416216,
              "magnitude": 1.0,
              "sqrMagnitude": 1.00000012
            },
            "magnitude": 2.20814919,
            "sqrMagnitude": 4.875923
          },
          "Control2": {
            "x": 1.795081,
            "y": -1.212349,
            "z": -0.428739,
            "normalized": {
              "x": 0.812934637,
              "y": -0.549034059,
              "z": -0.19416216,
              "magnitude": 1.0,
              "sqrMagnitude": 1.00000012
            },
            "magnitude": 2.20814919,
            "sqrMagnitude": 4.875923
          },
          "Alias": "1"
        },
        {
          "Position": {
            "x": 2.395694,
            "y": 1.222038,
            "z": -9.862594,
            "normalized": {
              "x": 0.234350547,
              "y": 0.119541675,
              "z": -0.96477437,
              "magnitude": 1.0,
              "sqrMagnitude": 1.0
            },
            "magnitude": 10.2226944,
            "sqrMagnitude": 104.503479
          },
          "ControlType": 1,
          "Control1": {
            "x": 1.672846,
            "y": 0.536385,
            "z": 6.061412,
            "normalized": {
              "x": 0.265074551,
              "y": 0.08499409,
              "z": 0.9604746,
              "magnitude": 1.0,
              "sqrMagnitude": 1.0
            },
            "magnitude": 6.31085062,
            "sqrMagnitude": 39.8268356
          },
          "Control2": {
            "x": -1.672846,
            "y": -0.536385,
            "z": -6.061412,
            "normalized": {
              "x": -0.265074551,
              "y": -0.08499409,
              "z": -0.9604746,
              "magnitude": 1.0,
              "sqrMagnitude": 1.0
            },
            "magnitude": 6.31085062,
            "sqrMagnitude": 39.8268356
          },
          "Alias": "2"
        },
        {
          "Position": {
            "x": -10.48096,
            "y": 4.08181,
            "z": -2.835074,
            "normalized": {
              "x": -0.9035669,
              "y": 0.35189414,
              "z": -0.244412631,
              "magnitude": 1.0,
              "sqrMagnitude": 1.00000012
            },
            "magnitude": 11.59954,
            "sqrMagnitude": 134.549332
          },
          "ControlType": 1,
          "Control1": {
            "x": -2.444495,
            "y": 1.420494,
            "z": -5.704852,
            "normalized": {
              "x": -0.383931965,
              "y": 0.22310254,
              "z": -0.896003067,
              "magnitude": 1.0,
              "sqrMagnitude": 1.0
            },
            "magnitude": 6.36700058,
            "sqrMagnitude": 40.5386963
          },
          "Control2": {
            "x": 2.444495,
            "y": -1.420494,
            "z": 5.704852,
            "normalized": {
              "x": 0.383931965,
              "y": -0.22310254,
              "z": 0.896003067,
              "magnitude": 1.0,
              "sqrMagnitude": 1.0
            },
            "magnitude": 6.36700058,
            "sqrMagnitude": 40.5386963
          },
          "Alias": "3"
        },
        {
          "ControlType": 1,
          "Control1": {
            "x": -3.238528,
            "z": 3.255112,
            "normalized": {
              "x": -0.705298662,
              "z": 0.708910346,
              "magnitude": 1.0,
              "sqrMagnitude": 1.00000012
            },
            "magnitude": 4.59171152,
            "sqrMagnitude": 21.0838165
          },
          "Control2": {
            "x": 3.238528,
            "z": -3.255112,
            "normalized": {
              "x": 0.705298662,
              "z": -0.708910346,
              "magnitude": 1.0,
              "sqrMagnitude": 1.00000012
            },
            "magnitude": 4.59171152,
            "sqrMagnitude": 21.0838165
          },
          "Alias": "End"
        }
      ],
      "Name": "Curve1",
      "RotY": 60.7679,
      "ID": 1,
      "PosX": 135.299,
      "PosY": 102.773,
      "PosZ": 341.915
    }
  ],
  "LittleGameList": []
}