{
  "OnInitSequece": [],
  "OnStartSequece": [
    {
      "TaskList": [
        {
          "$type": "RPG.GameCore.LockPlayerControl",
          "LockCameraControl": true,
          "LockInteractSelect": true,
          "TaskEnabled": true,
          "IsClientOnly": true
        },
        {
          "$type": "RPG.GameCore.PerformanceTransition",
          "SwitchInTime": 0.5,
          "SwitchKeepTime": 0.5,
          "CreateNpcList": [],
          "CaptureNpcList": [],
          "DestroyNpcList": [],
          "DisactiveVCamOnGraphEnd": true,
          "ActiveVirtualCamera": {
            "AreaName": "1020201_temp",
            "AnchorName": "Camera_102020102",
            "IsActive": true,
            "VCameraDitherMaxDistance": 1.0,
            "CenterPosX": -1.0,
            "CenterPosY": -1.0,
            "IsClientOnly": true
          },
          "SwitchCharacterAnchor": {
            "IsLocalPlayer": true,
            "AreaName": {
              "Value": "LevelArea_P20211_F20211001_G11"
            },
            "AnchorName": {
              "Value": "Anchor1"
            },
            "ResetAnimation": true,
            "ResetCamera": true,
            "ClearSpecialVision": true,
            "TaskEnabled": true,
            "IsClientOnly": true
          },
          "TaskEnabled": true,
          "IsClientOnly": true
        },
        {
          "$type": "RPG.GameCore.TriggerPerformance",
          "ValueSource": {},
          "PerformanceType": "C",
          "PerformanceID": 102020104,
          "TaskEnabled": true,
          "IsClientOnly": true
        },
        {
          "$type": "RPG.GameCore.UnLockPlayerControl",
          "UnLockCameraControl": true,
          "TaskEnabled": true,
          "IsClientOnly": true
        },
        {
          "$type": "RPG.GameCore.FinishPerformanceMission",
          "Key": "Mission_102020104",
          "TaskEnabled": true,
          "IsClientOnly": true
        }
      ]
    }
  ],
  "Type": "Mission"
}