{
  "OnInitSequece": [],
  "OnStartSequece": [
    {
      "TaskList": [
        {
          "$type": "RPG.GameCore.LevelPerformanceInitialize",
          "PerformanceType": "E",
          "HideMunicipalOther": true,
          "HideMonster": true,
          "ResetEnvironment": true,
          "ResetMonster": true,
          "TaskEnabled": true
        },
        {
          "$type": "RPG.GameCore.PlayFullScreenTransfer",
          "Type": "Black",
          "PrevDuration": 0.5,
          "KeepDuration": 0.5,
          "PostDuration": 0.5,
          "Action": [
            {
              "$type": "RPG.GameCore.ScrTrfActPerformance",
              "CreateNpc": {},
              "DestroyNpc": {
                "Hide": true
              },
              "CreateProp": {},
              "DestroyProp": {
                "TargetType": {
                  "$type": "RPG.GameCore.TargetFetchAdvPropEx"
                }
              },
              "CaptureNpc": [],
              "SwitchCharacterAnchor": {
                "ResetAnimation": true,
                "ResetCamera": true
              },
              "ActiveVirtualCamera": {
                "IsActive": true,
                "VCameraDitherMaxDistance": 1,
                "CenterPosX": -1,
                "CenterPosY": -1
              },
              "ActiveTemplateVirtualCamera": {
                "IsActive": true
              },
              "AdvNpcFaceToPlayer": {
                "FromDialog": true,
                "TryFaceToFace": true,
                "NpcLookAtPlayer": true,
                "PlayerLookAtNpc": true,
                "StopLookAtOnGraphEnd": true,
                "SteerImmediately": true,
                "WaitFinishMode": "WaitFaceAngle",
                "ForceToStandBy": true,
                "TaskEnabled": true
              }
            }
          ],
          "TaskEnabled": true
        },
        {
          "$type": "RPG.GameCore.PlayAndWaitSimpleTalk",
          "KeepDisplay": true,
          "SimpleTalkList": [
            {
              "TextSpeed": 20,
              "TalkSentenceID": 814120401,
              "ProtectTime": 0.8
            },
            {
              "TextSpeed": 20,
              "TalkSentenceID": 814120402,
              "ProtectTime": 0.8
            },
            {
              "TextSpeed": 20,
              "TalkSentenceID": 814120403,
              "ProtectTime": 0.8
            }
          ],
          "TaskEnabled": true
        },
        {
          "$type": "RPG.GameCore.EndPerformance",
          "TaskEnabled": true
        }
      ]
    },
    {
      "TaskList": [
        {
          "$type": "RPG.GameCore.WaitPerformanceEnd",
          "TaskEnabled": true
        },
        {
          "$type": "RPG.GameCore.FinishLevelGraph",
          "TaskEnabled": true
        }
      ]
    }
  ]
}