{
  "OnInitSequece": [],
  "OnStartSequece": [
    {
      "TaskList": [
        {
          "$type": "RPG.GameCore.WaitPerformanceEnd",
          "TaskEnabled": true,
          "IsClientOnly": true
        },
        {
          "$type": "RPG.GameCore.FinishLevelGraph",
          "TaskEnabled": true,
          "IsClientOnly": true
        }
      ]
    },
    {
      "TaskList": [
        {
          "$type": "RPG.GameCore.LevelPerformanceInitialize",
          "PerformanceType": "D",
          "CreateCharacterList": [],
          "EntityVisiableList": [],
          "HideMunicipalCrowd": true,
          "HideMunicipalPedestrian": true,
          "HideMunicipalOther": true,
          "HideMonster": true,
          "MarkStreamingItems": [],
          "ResetEnvironment": true,
          "ResetMonster": true,
          "TaskEnabled": true,
          "IsClientOnly": true
        },
        {
          "$type": "RPG.GameCore.PerformanceTransition",
          "SwitchInTime": 0.5,
          "SwitchKeepTime": 0.5,
          "SwitchOutTime": 0.5,
          "CreateNpcList": [],
          "DestroyNpcList": [],
          "CreateProp": {
            "GroupID": {},
            "GroupPropID": {},
            "IsClientOnly": true
          },
          "DestroyProp": {
            "TargetType": {
              "$type": "RPG.GameCore.TargetFetchAdvPropEx"
            },
            "ID": {},
            "GroupID": {},
            "IsClientOnly": true
          },
          "DisactiveVCamOnGraphEnd": true,
          "ActiveVirtualCamera": {
            "AreaName": "MainMission_2000301",
            "AnchorName": "Camera_2000104_02",
            "IsActive": true,
            "VCameraDitherMaxDistance": 1,
            "CenterPosX": -1,
            "CenterPosY": -1,
            "TaskEnabled": true,
            "IsClientOnly": true
          },
          "ActiveTemplateVirtualCamera": {
            "IsActive": true,
            "IsClientOnly": true
          },
          "SwitchCharacterAnchor": {
            "ResetAnimation": true,
            "ResetCamera": true,
            "IsClientOnly": true
          },
          "AdvNpcFaceToPlayer": {
            "FromDialog": true,
            "TryFaceToFace": true,
            "NpcLookAtPlayer": true,
            "PlayerLookAtNpc": true,
            "StopLookAtOnGraphEnd": true,
            "TurnBackOnGraphEnd": true,
            "WaitFinishMode": "WaitFaceAngle",
            "ForceToStandBy": true,
            "IsClientOnly": true
          },
          "TaskEnabled": true,
          "IsClientOnly": true
        },
        {
          "$type": "RPG.GameCore.PlayAndWaitSimpleTalk",
          "KeepDisplay": true,
          "SimpleTalkList": [
            {
              "TextSpeed": 20,
              "TalkSentenceID": 200023008,
              "ProtectTime": 0.3
            }
          ],
          "TaskEnabled": true,
          "IsClientOnly": true
        },
        {
          "$type": "RPG.GameCore.PlayOptionTalk",
          "OptionList": [
            {
              "TalkSentenceID": 200023009,
              "OptionIconType": "ChatContinueIcon",
              "TriggerCustomString": "TriggerTalkSentence_200023009"
            },
            {
              "TalkSentenceID": 200023011,
              "OptionIconType": "ChatContinueIcon",
              "TriggerCustomString": "TriggerTalkSentence_200023011"
            }
          ],
          "TaskEnabled": true,
          "IsClientOnly": true
        }
      ]
    },
    {
      "TaskList": [
        {
          "$type": "RPG.GameCore.WaitCustomString",
          "CustomString": {
            "Value": "TriggerTalkSentence_200023009"
          },
          "TaskEnabled": true
        },
        {
          "$type": "RPG.GameCore.PlayAndWaitSimpleTalk",
          "KeepDisplay": true,
          "SimpleTalkList": [
            {
              "TextSpeed": 20,
              "TalkSentenceID": 200023010,
              "ProtectTime": 0.3
            }
          ],
          "TaskEnabled": true,
          "IsClientOnly": true
        },
        {
          "$type": "RPG.GameCore.TriggerCustomString",
          "CustomString": {
            "Value": "TriggerTalkSentence_200023013"
          },
          "TaskEnabled": true
        }
      ]
    },
    {
      "TaskList": [
        {
          "$type": "RPG.GameCore.WaitCustomString",
          "CustomString": {
            "Value": "TriggerTalkSentence_200023011"
          },
          "TaskEnabled": true
        },
        {
          "$type": "RPG.GameCore.PlayAndWaitSimpleTalk",
          "KeepDisplay": true,
          "SimpleTalkList": [
            {
              "TextSpeed": 20,
              "TalkSentenceID": 200023012,
              "ProtectTime": 0.3
            }
          ],
          "TaskEnabled": true,
          "IsClientOnly": true
        },
        {
          "$type": "RPG.GameCore.TriggerCustomString",
          "CustomString": {
            "Value": "TriggerTalkSentence_200023013"
          },
          "TaskEnabled": true
        }
      ]
    },
    {
      "TaskList": [
        {
          "$type": "RPG.GameCore.WaitCustomString",
          "CustomString": {
            "Value": "TriggerTalkSentence_200023013"
          },
          "TaskEnabled": true
        },
        {
          "$type": "RPG.GameCore.PlayAndWaitSimpleTalk",
          "KeepDisplay": true,
          "SimpleTalkList": [
            {
              "TextSpeed": 20,
              "TalkSentenceID": 200023013,
              "ProtectTime": 0.3
            },
            {
              "TextSpeed": 20,
              "TalkSentenceID": 200023014,
              "ProtectTime": 0.3
            }
          ],
          "TaskEnabled": true,
          "IsClientOnly": true
        },
        {
          "$type": "RPG.GameCore.PlayOptionTalk",
          "OptionList": [
            {
              "TalkSentenceID": 200023015,
              "OptionIconType": "ChatContinueIcon",
              "TriggerCustomString": "TriggerTalkSentence_200023015"
            },
            {
              "TalkSentenceID": 200023017,
              "OptionIconType": "ChatContinueIcon",
              "TriggerCustomString": "TriggerTalkSentence_200023017"
            },
            {
              "TalkSentenceID": 200023019,
              "OptionIconType": "ChatContinueIcon",
              "TriggerCustomString": "TriggerTalkSentence_200023019"
            }
          ],
          "TaskEnabled": true,
          "IsClientOnly": true
        }
      ]
    },
    {
      "TaskList": [
        {
          "$type": "RPG.GameCore.WaitCustomString",
          "CustomString": {
            "Value": "TriggerTalkSentence_200023015"
          },
          "TaskEnabled": true
        },
        {
          "$type": "RPG.GameCore.PlayAndWaitSimpleTalk",
          "KeepDisplay": true,
          "SimpleTalkList": [
            {
              "TextSpeed": 20,
              "TalkSentenceID": 200023016,
              "ProtectTime": 0.3
            }
          ],
          "TaskEnabled": true,
          "IsClientOnly": true
        },
        {
          "$type": "RPG.GameCore.TriggerCustomString",
          "CustomString": {
            "Value": "TriggerTalkSentence_200023021"
          },
          "TaskEnabled": true
        }
      ]
    },
    {
      "TaskList": [
        {
          "$type": "RPG.GameCore.WaitCustomString",
          "CustomString": {
            "Value": "TriggerTalkSentence_200023017"
          },
          "TaskEnabled": true
        },
        {
          "$type": "RPG.GameCore.PlayAndWaitSimpleTalk",
          "KeepDisplay": true,
          "SimpleTalkList": [
            {
              "TextSpeed": 20,
              "TalkSentenceID": 200023018,
              "ProtectTime": 0.3
            }
          ],
          "TaskEnabled": true,
          "IsClientOnly": true
        },
        {
          "$type": "RPG.GameCore.TriggerCustomString",
          "CustomString": {
            "Value": "TriggerTalkSentence_200023021"
          },
          "TaskEnabled": true
        }
      ]
    },
    {
      "TaskList": [
        {
          "$type": "RPG.GameCore.WaitCustomString",
          "CustomString": {
            "Value": "TriggerTalkSentence_200023019"
          },
          "TaskEnabled": true
        },
        {
          "$type": "RPG.GameCore.PlayAndWaitSimpleTalk",
          "KeepDisplay": true,
          "SimpleTalkList": [
            {
              "TextSpeed": 20,
              "TalkSentenceID": 200023020,
              "ProtectTime": 0.3
            }
          ],
          "TaskEnabled": true,
          "IsClientOnly": true
        },
        {
          "$type": "RPG.GameCore.PlayOptionTalk",
          "OptionList": [
            {
              "TalkSentenceID": 200023021,
              "OptionIconType": "ChatContinueIcon",
              "TriggerCustomString": "TriggerTalkSentence_200023021"
            },
            {
              "TalkSentenceID": 200023022,
              "OptionIconType": "ChatContinueIcon",
              "TriggerCustomString": "TriggerTalkSentence_200023021"
            },
            {
              "TalkSentenceID": 200023023,
              "OptionIconType": "ChatContinueIcon",
              "TriggerCustomString": "TriggerTalkSentence_200023021"
            }
          ],
          "TaskEnabled": true,
          "IsClientOnly": true
        }
      ]
    },
    {
      "TaskList": [
        {
          "$type": "RPG.GameCore.WaitCustomString",
          "CustomString": {
            "Value": "TriggerTalkSentence_200023021"
          },
          "TaskEnabled": true
        },
        {
          "$type": "RPG.GameCore.PlayAndWaitSimpleTalk",
          "KeepDisplay": true,
          "SimpleTalkList": [
            {
              "TextSpeed": 20,
              "TalkSentenceID": 200023024,
              "ProtectTime": 0.3
            }
          ],
          "TaskEnabled": true,
          "IsClientOnly": true
        },
        {
          "$type": "RPG.GameCore.PerformanceTransition",
          "SwitchInTime": 0.5,
          "SwitchKeepTime": 0.5,
          "SwitchOutTime": 0.5,
          "CreateNpcList": [],
          "DestroyNpcList": [],
          "CreateProp": {
            "GroupID": {},
            "GroupPropID": {},
            "IsClientOnly": true
          },
          "DestroyProp": {
            "TargetType": {
              "$type": "RPG.GameCore.TargetFetchAdvPropEx"
            },
            "ID": {},
            "GroupID": {},
            "IsClientOnly": true
          },
          "DisactiveVCamOnGraphEnd": true,
          "ActiveVirtualCamera": {
            "AreaName": "MainMission_2000301",
            "AnchorName": "Camera_2000104_02",
            "VCameraDitherMaxDistance": 1,
            "CenterPosX": -1,
            "CenterPosY": -1,
            "TaskEnabled": true,
            "IsClientOnly": true
          },
          "ActiveTemplateVirtualCamera": {
            "IsActive": true,
            "IsClientOnly": true
          },
          "SwitchCharacterAnchor": {
            "ResetAnimation": true,
            "ResetCamera": true,
            "IsClientOnly": true
          },
          "AdvNpcFaceToPlayer": {
            "FromDialog": true,
            "TryFaceToFace": true,
            "NpcLookAtPlayer": true,
            "PlayerLookAtNpc": true,
            "StopLookAtOnGraphEnd": true,
            "TurnBackOnGraphEnd": true,
            "WaitFinishMode": "WaitFaceAngle",
            "ForceToStandBy": true,
            "IsClientOnly": true
          },
          "TaskEnabled": true,
          "IsClientOnly": true
        },
        {
          "$type": "RPG.GameCore.EndPerformance",
          "TaskEnabled": true,
          "IsClientOnly": true
        }
      ]
    }
  ]
}