{
  "OnInitSequece": [],
  "OnStartSequece": [
    {
      "TaskList": [
        {
          "$type": "RPG.GameCore.LevelPerformanceInitialize",
          "PerformanceType": "D",
          "CreateCharacterList": [],
          "CaptureNPCList": [],
          "EntityVisiableList": [],
          "HideMunicipalOther": true,
          "HideMonster": true,
          "PropVisiableList": [],
          "StreamingSourcesInBlackMask": [],
          "StreamingSourcesAfterBlackMask": [],
          "MarkStreamingItems": [],
          "ResetEnvironment": true,
          "ResetMonster": true,
          "TaskEnabled": true
        },
        {
          "$type": "RPG.GameCore.AdvNpcFaceToPlayer",
          "FromDialog": true,
          "TryFaceToFace": true,
          "NpcLookAtPlayer": true,
          "PlayerLookAtNpc": true,
          "StopLookAtOnGraphEnd": true,
          "TurnBackOnGraphEnd": true,
          "WaitFinishMode": "WaitFaceAngle",
          "ForceToStandBy": true,
          "TaskEnabled": true
        },
        {
          "$type": "RPG.GameCore.PlayAndWaitSimpleTalk",
          "KeepDisplay": true,
          "SimpleTalkList": [
            {
              "TextSpeed": 20,
              "TalkSentenceID": 103020651,
              "ProtectTime": 0.3
            }
          ],
          "TaskEnabled": true
        },
        {
          "$type": "RPG.GameCore.TriggerCustomString",
          "CustomString": {
            "Value": "Wait_Option_103020127_166"
          },
          "TaskEnabled": true
        }
      ]
    },
    {
      "IsLoop": true,
      "TaskList": [
        {
          "$type": "RPG.GameCore.WaitCustomString",
          "CustomString": {
            "Value": "Wait_Option_103020127_166"
          },
          "TaskEnabled": true
        },
        {
          "$type": "RPG.GameCore.PlayOptionTalk",
          "OptionList": [
            {
              "TalkSentenceID": 103020652,
              "OptionIconType": "ChatLoopIcon",
              "TriggerCustomString": "TalkSentence_103020653"
            },
            {
              "TalkSentenceID": 103020655,
              "OptionIconType": "ChatLoopIcon",
              "TriggerCustomString": "TalkSentence_103020656"
            },
            {
              "TalkSentenceID": 103020658,
              "OptionIconType": "ChatLoopIcon",
              "TriggerCustomString": "TalkSentence_103020659"
            },
            {
              "TalkSentenceID": 103020661,
              "OptionIconType": "ChatOutIcon",
              "TriggerCustomString": "TalkSentence_103020662"
            }
          ],
          "HideSelected": true,
          "TaskEnabled": true
        }
      ]
    },
    {
      "IsLoop": true,
      "TaskList": [
        {
          "$type": "RPG.GameCore.WaitCustomString",
          "CustomString": {
            "Value": "TalkSentence_103020653"
          },
          "TaskEnabled": true
        },
        {
          "$type": "RPG.GameCore.PlayAndWaitSimpleTalk",
          "KeepDisplay": true,
          "SimpleTalkList": [
            {
              "TextSpeed": 20,
              "TalkSentenceID": 103020653,
              "ProtectTime": 0.3
            },
            {
              "TextSpeed": 20,
              "TalkSentenceID": 103020654,
              "ProtectTime": 0.3
            }
          ],
          "TaskEnabled": true
        },
        {
          "$type": "RPG.GameCore.TriggerCustomString",
          "CustomString": {
            "Value": "Wait_Option_103020127_166"
          },
          "TaskEnabled": true
        }
      ]
    },
    {
      "IsLoop": true,
      "TaskList": [
        {
          "$type": "RPG.GameCore.WaitCustomString",
          "CustomString": {
            "Value": "TalkSentence_103020656"
          },
          "TaskEnabled": true
        },
        {
          "$type": "RPG.GameCore.PlayAndWaitSimpleTalk",
          "KeepDisplay": true,
          "SimpleTalkList": [
            {
              "TextSpeed": 20,
              "TalkSentenceID": 103020656,
              "ProtectTime": 0.3
            },
            {
              "TextSpeed": 20,
              "TalkSentenceID": 103020657,
              "ProtectTime": 0.3
            }
          ],
          "TaskEnabled": true
        },
        {
          "$type": "RPG.GameCore.TriggerCustomString",
          "CustomString": {
            "Value": "Wait_Option_103020127_166"
          },
          "TaskEnabled": true
        }
      ]
    },
    {
      "IsLoop": true,
      "TaskList": [
        {
          "$type": "RPG.GameCore.WaitCustomString",
          "CustomString": {
            "Value": "TalkSentence_103020659"
          },
          "TaskEnabled": true
        },
        {
          "$type": "RPG.GameCore.PlayAndWaitSimpleTalk",
          "KeepDisplay": true,
          "SimpleTalkList": [
            {
              "TextSpeed": 20,
              "TalkSentenceID": 103020659,
              "ProtectTime": 0.3
            },
            {
              "TextSpeed": 20,
              "TalkSentenceID": 103020660,
              "ProtectTime": 0.3
            }
          ],
          "TaskEnabled": true
        },
        {
          "$type": "RPG.GameCore.TriggerCustomString",
          "CustomString": {
            "Value": "Wait_Option_103020127_166"
          },
          "TaskEnabled": true
        }
      ]
    },
    {
      "TaskList": [
        {
          "$type": "RPG.GameCore.WaitCustomString",
          "CustomString": {
            "Value": "TalkSentence_103020662"
          },
          "TaskEnabled": true
        },
        {
          "$type": "RPG.GameCore.PlayAndWaitSimpleTalk",
          "KeepDisplay": true,
          "SimpleTalkList": [
            {
              "TextSpeed": 20,
              "TalkSentenceID": 103020662,
              "ProtectTime": 0.3
            }
          ],
          "TaskEnabled": true
        },
        {
          "$type": "RPG.GameCore.EndPerformance",
          "TaskEnabled": true
        }
      ]
    },
    {
      "TaskList": [
        {
          "$type": "RPG.GameCore.WaitPerformanceEnd",
          "TaskEnabled": true
        },
        {
          "$type": "RPG.GameCore.FinishLevelGraph",
          "TaskEnabled": true
        }
      ]
    }
  ]
}