[
  {
    "SkillList": [
      100111,
      100112,
      100113
    ],
    "PhasePic": "",
    "PhaseAnswer": {
      "Hash": -252846129
    },
    "Difficulty": 1,
    "PhaseDescription": {
      "Hash": 567174221
    },
    "PhaseName": {
      "Hash": 1895867854
    },
    "PhaseID": 10011
  },
  {
    "SkillList": [
      100121,
      100122
    ],
    "PhasePic": "",
    "PhaseAnswer": {
      "Hash": -252846130
    },
    "Difficulty": 1,
    "PhaseDescription": {
      "Hash": -998909720
    },
    "PhaseName": {
      "Hash": 1895867855
    },
    "PhaseID": 10012
  },
  {
    "SkillList": [
      100211,
      100212
    ],
    "PhasePic": "",
    "PhaseAnswer": {
      "Hash": 1313237812
    },
    "Difficulty": 1,
    "PhaseDescription": {
      "Hash": 567174218
    },
    "PhaseName": {
      "Hash": -833015501
    },
    "PhaseID": 10021
  },
  {
    "SkillList": [
      100221,
      100222
    ],
    "PhasePic": "",
    "PhaseAnswer": {
      "Hash": 1313237811
    },
    "Difficulty": 1,
    "PhaseDescription": {
      "Hash": -998909723
    },
    "PhaseName": {
      "Hash": -833015500
    },
    "PhaseID": 10022
  },
  {
    "SkillList": [
      100311,
      100312,
      100313
    ],
    "PhasePic": "",
    "PhaseAnswer": {
      "Hash": -1415645543
    },
    "Difficulty": 1,
    "PhaseDescription": {
      "Hash": 567174219
    },
    "PhaseName": {
      "Hash": 733068440
    },
    "PhaseID": 10031
  },
  {
    "SkillList": [
      100411,
      100412,
      100413
    ],
    "PhasePic": "",
    "PhaseAnswer": {
      "Hash": 150438398
    },
    "Difficulty": 1,
    "PhaseDescription": {
      "Hash": 567174224
    },
    "PhaseName": {
      "Hash": -1639584555
    },
    "PhaseID": 10041
  },
  {
    "SkillList": [
      100421,
      100422,
      100423
    ],
    "PhasePic": "",
    "PhaseAnswer": {
      "Hash": 150438397
    },
    "Difficulty": 1,
    "PhaseDescription": {
      "Hash": -998909717
    },
    "PhaseName": {
      "Hash": -1639584554
    },
    "PhaseID": 10042
  },
  {
    "SkillList": [
      100511
    ],
    "PhasePic": "",
    "PhaseAnswer": {
      "Hash": 1716522339
    },
    "Difficulty": 1,
    "PhaseDescription": {
      "Hash": 567174225
    },
    "PhaseName": {
      "Hash": -73500614
    },
    "PhaseID": 10051
  },
  {
    "SkillList": [
      100521
    ],
    "PhasePic": "",
    "PhaseAnswer": {
      "Hash": 1716522338
    },
    "Difficulty": 1,
    "PhaseDescription": {
      "Hash": -998909716
    },
    "PhaseName": {
      "Hash": -73500613
    },
    "PhaseID": 10052
  },
  {
    "SkillList": [
      100611,
      100612,
      100613
    ],
    "PhasePic": "",
    "PhaseAnswer": {
      "Hash": -1012361016
    },
    "Difficulty": 1,
    "PhaseDescription": {
      "Hash": 567174222
    },
    "PhaseName": {
      "Hash": 1492583327
    },
    "PhaseID": 10061
  },
  {
    "SkillList": [
      100621
    ],
    "PhasePic": "",
    "PhaseAnswer": {
      "Hash": -1012361017
    },
    "Difficulty": 1,
    "PhaseDescription": {
      "Hash": -998909719
    },
    "PhaseName": {
      "Hash": 1492583328
    },
    "PhaseID": 10062
  }
]